Metadata-Version: 2.4
Name: az-smart-logger
Version: 1.0.5
Summary: Smart Logger library for Python projects with FastAPI, Flask, and Django support
Home-page: https://github.com/ShahabazAlam/smart-logger
Author: Shahabaz Alam
Author-email: Shahabaz Alam <shahabazalam1@gmail.com>
License: MIT
Requires-Python: >=3.8
License-File: LICENSE
Requires-Dist: annotated-types==0.7.0
Requires-Dist: anyio==4.10.0
Requires-Dist: argon2-cffi==25.1.0
Requires-Dist: argon2-cffi-bindings==25.1.0
Requires-Dist: cffi==2.0.0
Requires-Dist: click==8.2.1
Requires-Dist: fastapi==0.116.1
Requires-Dist: h11==0.16.0
Requires-Dist: httptools==0.6.4
Requires-Dist: idna==3.10
Requires-Dist: Jinja2==3.1.6
Requires-Dist: markdown-it-py==4.0.0
Requires-Dist: MarkupSafe==3.0.2
Requires-Dist: mdurl==0.1.2
Requires-Dist: passlib==1.7.4
Requires-Dist: pycparser==2.23
Requires-Dist: pydantic==2.11.7
Requires-Dist: pydantic_core==2.33.2
Requires-Dist: Pygments==2.19.2
Requires-Dist: PyJWT==2.10.1
Requires-Dist: python-dotenv==1.1.1
Requires-Dist: PyYAML==6.0.2
Requires-Dist: rich==14.1.0
Requires-Dist: shellingham==1.5.4
Requires-Dist: sniffio==1.3.1
Requires-Dist: SQLAlchemy==2.0.43
Requires-Dist: typer==0.17.4
Requires-Dist: typing_extensions==4.15.0
Requires-Dist: typing-inspection==0.4.1
Requires-Dist: uvicorn[standard]>=0.23.0
Requires-Dist: uvloop==0.21.0
Requires-Dist: watchfiles==1.1.0
Requires-Dist: websockets==15.0.1
Requires-Dist: psutil==7.1.0
Requires-Dist: python-socketio[asyncio_server]==5.13.0
Dynamic: author
Dynamic: home-page
Dynamic: license-file
Dynamic: requires-python
